uncouple/__init__.py
uncouple/config.py
uncouple/fieldtypes/addr.py
uncouple/fieldtypes/configtable.py
uncouple/fieldtypes/readyaml.py
uncouple/fieldtypes/stringlist.py
uncouple/fieldtypes/url.py
uncouple-1.0.0.dist-info/METADATA
uncouple-1.0.0.dist-info/WHEEL
uncouple-1.0.0.dist-info/RECORD
