Metadata-Version: 2.4
Name: uncouple
Version: 1.0.0
Summary: Configuration parameter handling library
Author-email: Sebastian Acuna <sebastian@unholster.com>
Requires-Python: >=3.10
Requires-Dist: pydantic>=2.6.1
Requires-Dist: python-decouple>=3.8
Requires-Dist: pyyaml>=6.0.1
Requires-Dist: yarl>=1.9.4
Provides-Extra: dev
Requires-Dist: pytest>=8.0.0; extra == 'dev'
Requires-Dist: ruff>=0.2.1; extra == 'dev'
